prestornado/__init__.py
prestornado/common.py
prestornado/exc.py
prestornado/presto.py
prestornado-0.1.10.dist-info/DESCRIPTION.rst
prestornado-0.1.10.dist-info/METADATA
prestornado-0.1.10.dist-info/RECORD
prestornado-0.1.10.dist-info/WHEEL
prestornado-0.1.10.dist-info/metadata.json
prestornado-0.1.10.dist-info/pbr.json
prestornado-0.1.10.dist-info/top_level.txt
