Metadata-Version: 2.0
Name: prestornado
Version: 0.1.10
Summary: Asynchronous PrestoDB DB-API for Tornado Web Server
Home-page: https://github.com/jianingy/prestornado
Author: Jianing Yang
Author-email: jianingy.yang@gmail.com
License: UNKNOWN
Platform: UNKNOWN
Classifier: Intended Audience :: Developers
Classifier: License :: OSI Approved :: Apache Software License
Classifier: Operating System :: OS Independent
Classifier: Topic :: Database
Requires-Dist: tornado (>=4.3)
